cli_tool/__init__.py
cli_tool/basic_commands.py
cli_tool/cli.py
cli_tool/config.py
cli_tool/loader.py
cli_tool/main.py
cli_tool/storage_provider.py
atari_monk_cli_tool-0.1.2.dist-info/METADATA
atari_monk_cli_tool-0.1.2.dist-info/WHEEL
atari_monk_cli_tool-0.1.2.dist-info/entry_points.txt
atari_monk_cli_tool-0.1.2.dist-info/top_level.txt
atari_monk_cli_tool-0.1.2.dist-info/RECORD
