Metadata-Version: 2.1
Name: atari-monk-cli-tool
Version: 0.1.2
Summary: A modular CLI application that supports dynamic command sets.
Home-page: https://github.com/atari-monk/cli_tool
Author: atari monk
Author-email: atari.monk1@gmail.com
Classifier: Programming Language :: Python :: 3
Classifier: License :: OSI Approved :: MIT License
Requires-Python: >=3.12.0
Requires-Dist: atari-monk-cli-logger
Requires-Dist: atari-monk-keyval-storage
Requires-Dist: atari-monk-cli-tool-commands
